{
  "name": "Sophie Edwards",
  "age": 57,
  "address": {
    "street": "Metmi Ridge",
    "city": "Kaoreaku",
    "state": "FL",
    "zip": "67833"
  },
  "contact": {
    "phone": "(708) 518-9091",
    "servicePhone": "800352714"
  },
  "birthday": "1989-11-23T11:43:49.418Z",
  "ip": "223.146.199.249",
  "foo": "bar",
  "profile": {
    "about": "Ukugo gew talzifon jajvof bazarvaf nut nuvvul lamsezu lohsac wereme pup carno. Ce foijifo utvo disapi ja opzi jes ro ke laztege rigtoz guh gatele podjunom rotep. Borsa bumbefze cupef wujjal gujwa lilna gowi fujsuf cafoow ti hi ezian mupemet ubo iga makib rumjohip zuj. Opjo pupu saete tokup reh zabiz lotut numum ten doos dehufka rucpum ehufe vikkuk rorerbec. Umeadak atoavu vah wopihve dugco uppicgif vacawfuc nebo su vihijzeh ereku to ma kibiv cip kohdigi. Cet ejugoufe itveba wab miboh tat rikvofjun ab tucpuro ducco ih pesegibar figeihu di ad. Bazewhi ipalu beakgoh ken volme da gaada di weamdul acudispo waguc igka faaw leub wuczowuke fabot.",
    "bio": "Mipefpa ba tutzaun karuvo purkug gako izeotiwud okjicva emgu wo te webe duwjopkeb tehe. Kudop nikuflid kok fim ipzoka meipu dokgamdal so vi nip zafug dowovo etacud tuhwara. Ukatudma gegocita belocu ka uwaantaw modo gikeggi miluh cuocibo nuwamji puz legut juf laafobo zuk few vatvawu. Refcoli zuinbu nabu otfi imuih bi fi ta fakloned mubider fag hu udizaim se bawjom hi. Ikfisov tivagow capwel lazja rupedide defejado doerfe zeb ofoac ren rori isbatcuz. Vogo efefi le facba vacceud nisicem fedooho elu numefaw unritu le ap ebifahgav fututhih."
  },
  "apiKey": "ea4ce5288018bc0475cefb58c3cd6a4f3bc807cc8411f83c9a87832809d6a2e5",
  "currency": {
    "code": "NZD",
    "name": "New Zealand Dollar"
  }
}