{
  "name": "Mattie Cannon",
  "age": 36,
  "address": {
    "street": "Fotaw Road",
    "city": "Sewijsa",
    "state": "IL",
    "zip": "98598"
  },
  "contact": {
    "phone": "(283) 458-7537",
    "servicePhone": "800582498"
  },
  "birthday": "1975-08-02T13:33:30.003Z",
  "ip": "146.209.134.146",
  "foo": "bar",
  "profile": {
    "about": "Esi of koegave za mi finec toirwel tod kizul naini kaihipe zepotpa omsaglid to vavik baus. Gih urubitej zom esusoj vula navhova ocfecsi bapigu zuhsu nuocba budo bese getiawe cacivdum zujevrek. Pi sahi cealta febwa oniid maj usadif ofar zah nebaki bimic pew ulkewi tatojuz bezukri muacu henod pakiz.",
    "bio": "Fohziozu ni vojhuvbu bo okopo usziwji hel kinej kaizuf bu nav fome bif. Zom fenkeho moloiza dizvilo kuace suk kacofa ij asgu jejgokfar beja sujwo. Jirca wuhoz ah usiuhu muw wim zac lihro omo remalvun lu nisku sojij opawrab asage cefduk cer gi."
  },
  "apiKey": "8622d4e15311489a7c26989179640c5955c19941a8573bdf13de4c4cf6328bf0",
  "currency": {
    "code": "FJD",
    "name": "Fiji Dollar"
  }
}